aioserial/__init__.py
aioserial/aioserial.py
aioserial-1.2.2.dist-info/LICENSE
aioserial-1.2.2.dist-info/WHEEL
aioserial-1.2.2.dist-info/METADATA
aioserial-1.2.2.dist-info/RECORD
