Metadata-Version: 2.1
Name: aioserial
Version: 1.2.2
Summary: An asynchronous serial port library of Python
Home-page: https://github.com/changyuheng/aioserial
License: MPL-2.0
Author: Henry Chang
Author-email: mr.changyuheng@gmail.com
Requires-Python: >=3.6,<4.0
Classifier: License :: OSI Approved
Classifier: Programming Language :: Python :: 3
Classifier: Programming Language :: Python :: 3.6
Classifier: Programming Language :: Python :: 3.7
Classifier: Programming Language :: Python :: 3.8
Requires-Dist: pyserial
